{"chunk_definitions":[{"row":30,"row_count":1,"visible":true,"expansion_state":0,"options":{"engine":"r","label":"cars"},"document_id":"9749EA9B","chunk_id":"cm353kh3vs7ev","chunk_label":"cars"},{"row":53,"row_count":1,"visible":true,"expansion_state":0,"options":{"engine":"r","label":"unnamed-chunk-283"},"document_id":"9749EA9B","chunk_id":"cibp2wbt894xi","chunk_label":"unnamed-chunk-1"},{"row":72,"row_count":1,"visible":true,"expansion_state":0,"options":{"engine":"r","label":"unnamed-chunk-300"},"document_id":"9749EA9B","chunk_id":"cgt2az4djvxcc","chunk_label":"unnamed-chunk-2"},{"row":104,"row_count":1,"visible":true,"expansion_state":0,"options":{"engine":"r","label":"setup","include":false},"document_id":"9749EA9B","chunk_id":"csetup_chunk","chunk_label":"setup"},{"row":135,"row_count":1,"visible":true,"expansion_state":0,"options":{"engine":"r","label":"unnamed-chunk-292"},"document_id":"9749EA9B","chunk_id":"csdq4dxccoctm","chunk_label":"unnamed-chunk-3"},{"row":144,"row_count":1,"visible":true,"expansion_state":0,"options":{"engine":"r","label":"unnamed-chunk-301"},"document_id":"9749EA9B","chunk_id":"cckz8w5e1j8w8","chunk_label":"unnamed-chunk-4"},{"row":156,"row_count":1,"visible":true,"expansion_state":0,"options":{"engine":"r","label":"unnamed-chunk-302"},"document_id":"9749EA9B","chunk_id":"cwsiwhz0zmgtm","chunk_label":"unnamed-chunk-5"},{"row":192,"row_count":1,"visible":true,"expansion_state":0,"options":{"engine":"r","label":"unnamed-chunk-303"},"document_id":"9749EA9B","chunk_id":"cwhl83hotajva","chunk_label":"unnamed-chunk-6"},{"row":201,"row_count":1,"visible":true,"expansion_state":0,"options":{"engine":"r","label":"unnamed-chunk-304"},"document_id":"9749EA9B","chunk_id":"cyw8medem1mco","chunk_label":"unnamed-chunk-7"},{"row":238,"row_count":1,"visible":true,"expansion_state":0,"options":{"engine":"r","label":"unnamed-chunk-305"},"document_id":"9749EA9B","chunk_id":"cme5cazogvuxt","chunk_label":"unnamed-chunk-8"},{"row":262,"row_count":1,"visible":true,"expansion_state":0,"options":{"engine":"r","label":"unnamed-chunk-314"},"document_id":"9749EA9B","chunk_id":"c554b6ok3spmo","chunk_label":"unnamed-chunk-9"},{"row":279,"row_count":1,"visible":true,"expansion_state":0,"options":{"engine":"r","label":"unnamed-chunk-315"},"document_id":"9749EA9B","chunk_id":"crjoon5lzsuh7","chunk_label":"unnamed-chunk-10"},{"row":309,"row_count":1,"visible":true,"expansion_state":0,"options":{"engine":"r","label":"unnamed-chunk-326"},"document_id":"9749EA9B","chunk_id":"c1du00yvs5dfo","chunk_label":"unnamed-chunk-11"},{"row":329,"row_count":1,"visible":true,"expansion_state":0,"options":{"engine":"r","label":"unnamed-chunk-353"},"document_id":"9749EA9B","chunk_id":"c6nvpslxf3exu","chunk_label":"unnamed-chunk-12"},{"row":340,"row_count":1,"visible":true,"expansion_state":0,"options":{"engine":"r","label":"unnamed-chunk-355"},"document_id":"9749EA9B","chunk_id":"csx5ytazpo6l3","chunk_label":"unnamed-chunk-13"},{"row":362,"row_count":1,"visible":true,"expansion_state":0,"options":{"engine":"r","label":"unnamed-chunk-356"},"document_id":"9749EA9B","chunk_id":"chghazq62b5sv","chunk_label":"unnamed-chunk-14"},{"row":370,"row_count":1,"visible":true,"expansion_state":0,"options":{"engine":"r","label":"unnamed-chunk-330"},"document_id":"9749EA9B","chunk_id":"cvcp7oilk93a1","chunk_label":"unnamed-chunk-15"},{"row":390,"row_count":1,"visible":true,"expansion_state":0,"options":{"engine":"r","label":"unnamed-chunk-361"},"document_id":"9749EA9B","chunk_id":"cxq5wobzg0i8b","chunk_label":"unnamed-chunk-17"},{"row":407,"row_count":1,"visible":true,"expansion_state":0,"options":{"engine":"r","label":"unnamed-chunk-381"},"document_id":"9749EA9B","chunk_id":"c7uey6449uqcr","chunk_label":"unnamed-chunk-18"},{"row":432,"row_count":1,"visible":true,"expansion_state":0,"options":{"engine":"r","label":"unnamed-chunk-387"},"document_id":"9749EA9B","chunk_id":"cvzxy83arsmmj","chunk_label":"unnamed-chunk-19"},{"row":463,"row_count":1,"visible":true,"expansion_state":0,"options":{"engine":"r","label":"unnamed-chunk-392"},"document_id":"9749EA9B","chunk_id":"cs72o4v2jelep","chunk_label":"unnamed-chunk-20"},{"row":485,"row_count":1,"visible":true,"expansion_state":0,"options":{"engine":"r","label":"unnamed-chunk-393"},"document_id":"9749EA9B","chunk_id":"c8p7lt2tnhas4","chunk_label":"unnamed-chunk-21"},{"row":496,"row_count":1,"visible":true,"expansion_state":0,"options":{"engine":"r","label":"unnamed-chunk-394"},"document_id":"9749EA9B","chunk_id":"crn6t38g5h59b","chunk_label":"unnamed-chunk-22"},{"row":505,"row_count":1,"visible":true,"expansion_state":0,"options":{"engine":"r","label":"unnamed-chunk-395"},"document_id":"9749EA9B","chunk_id":"ccgd68kfsyfbt","chunk_label":"unnamed-chunk-23"},{"row":525,"row_count":1,"visible":true,"expansion_state":0,"options":{"engine":"r","label":"unnamed-chunk-404"},"document_id":"9749EA9B","chunk_id":"cqnxu9bwk4c2f","chunk_label":"unnamed-chunk-24"},{"row":535,"row_count":1,"visible":true,"expansion_state":0,"options":{"engine":"r","label":"unnamed-chunk-407"},"document_id":"9749EA9B","chunk_id":"c2jpg2gj4usyd","chunk_label":"unnamed-chunk-25"},{"row":551,"row_count":1,"visible":true,"expansion_state":0,"options":{"engine":"r","label":"unnamed-chunk-408"},"document_id":"9749EA9B","chunk_id":"cdhpcbt2tde1z","chunk_label":"unnamed-chunk-26"},{"row":590,"row_count":1,"visible":true,"expansion_state":0,"options":{"engine":"r","label":"unnamed-chunk-418"},"document_id":"9749EA9B","chunk_id":"cy7v99ip9bnmk","chunk_label":"unnamed-chunk-27"},{"row":619,"row_count":1,"visible":true,"expansion_state":0,"options":{"engine":"r","label":"unnamed-chunk-430"},"document_id":"9749EA9B","chunk_id":"cfk8k9g2c6rs2","chunk_label":"unnamed-chunk-28"},{"row":630,"row_count":1,"visible":true,"expansion_state":0,"options":{"engine":"r","label":"unnamed-chunk-433"},"document_id":"9749EA9B","chunk_id":"cp6hxa2d2aql1","chunk_label":"unnamed-chunk-29"},{"row":648,"row_count":1,"visible":true,"expansion_state":0,"options":{"engine":"r","label":"unnamed-chunk-437"},"document_id":"9749EA9B","chunk_id":"cw1t9tm757oy7","chunk_label":"unnamed-chunk-30"},{"row":656,"row_count":1,"visible":true,"expansion_state":0,"options":{"engine":"r","label":"unnamed-chunk-438"},"document_id":"9749EA9B","chunk_id":"c8ucrb51pq0yi","chunk_label":"unnamed-chunk-31"},{"row":669,"row_count":1,"visible":true,"expansion_state":0,"options":{"engine":"r","label":"unnamed-chunk-440"},"document_id":"9749EA9B","chunk_id":"c66btlx8vljh9","chunk_label":"unnamed-chunk-32"},{"row":685,"row_count":1,"visible":true,"expansion_state":0,"options":{"engine":"r","label":"unnamed-chunk-441"},"document_id":"9749EA9B","chunk_id":"c723rwwdwzb84","chunk_label":"unnamed-chunk-33"},{"row":722,"row_count":1,"visible":true,"expansion_state":0,"options":{"engine":"r","label":"unnamed-chunk-451"},"document_id":"9749EA9B","chunk_id":"cdp5hpmni9brm","chunk_label":"unnamed-chunk-34"}],"doc_write_time":1662513868,"chunk_rendered_width":644,"working_dir":null,"default_chunk_options":{}}